{
  "info": {
    "title": "Tarrasch vs Thorold (Manchester 1890)",
    "white": "Tarrasch Siegbert",
    "black": "Thorold, E.",
    "event": "Manchester",
    "date": "1890",
    "result": "1-0",
    "description": "Una partida instructiva donde Tarrasch demuestra principios clásicos de desarrollo, actividad de piezas y técnica en el final. Destaca el uso de la torre en séptima y la conversión precisa de una ventaja material."
  },
  "pgn": "1. e4 e6 2. d4 d5 3. Nd2 c5 4. exd5 Qxd5 5. Ngf3 cxd4 6. Bc4 Qh5 7. O-O Nc6 8. Nb3 e5 9. Nxe5 Qxd1 10. Rxd1 Nxe5 11. Re1 f6 12. f4 Bb4 13. Bd2 Bxd2 14. Nxd2 Bf5 15. fxe5 O-O-O 16. Bd3 Bxd3 17. cxd3 fxe5 18. Rac1+ Kb8 19. Rxe5 Nf6 20. Rce1 Rhe8 21. Rxe8 Nxe8 22. Re7 a6 23. Nb3 b6 24. Nxd4 Rxd4 25. Rxe8+ Kc7 26. Re3 Kd7 27. Kf2 g6 28. Rh3 h5 29. Ke3 Rd6 30. d4 Re6+ 31. Kd3 Re1 32. Rg3 Re6 33. Re3 Rd6 34. Re5 Rf6 35. a4 Rf2 36. Re2 Rf6 37. b4 Rf1 38. Re5 Rf2 39. Rg5 Rf6 40. h3 Kd6 41. Ke4 Re6+ 42. Re5 Rf6 43. d5 Kd7 44. Rg5 Kd6 45. Rg3 Ke7 46. Rf3 Rd6 47. Ke5 Rd8 48. d6+ Kd7 49. Rf7+ Kc8 50. Rc7+ Kb8 51. Rc2 Re8+ 52. Kf6 b5 53. d7 Rh8 54. Ke7 Rh7+ 55. Kd6 Rh8 56. Re2",
  "analysis": [
    {
      "san": "e4",
      "title": "1. e4 — Control central inmediato",
      "explanation": "Las blancas ocupan el centro y abren líneas para el alfil y la dama. Este movimiento es la base de muchas aperturas abiertas y permite un desarrollo rápido. También limita las opciones negras en el centro.",
      "pros": "Control central, desarrollo rápido, apertura de líneas.",
      "cons": "Puede ser atacado posteriormente por ...d5 o ...e5."
    },
    {
      "san": "e6",
      "title": "1... e6 — Preparando la Defensa Francesa",
      "explanation": "Las negras preparan ...d5 para disputar el centro. Este sistema es sólido y flexible. Mantiene una estructura firme aunque limita el alfil de c8 temporalmente.",
      "pros": "Estructura sólida, prepara ...d5.",
      "cons": "Alfil de c8 queda bloqueado."
    },
    {
      "san": "d4",
      "title": "2. d4 — Dominio del centro",
      "explanation": "Las blancas refuerzan el control central con dos peones. Esto da mayor espacio y opciones estratégicas. Es una continuación natural tras e4.",
      "pros": "Fuerte control central, más espacio.",
      "cons": "Puede ser objetivo de ataque."
    },
    {
      "san": "d5",
      "title": "2... d5 — Contraataque central",
      "explanation": "Las negras desafían inmediatamente el centro blanco. Esto define la estructura típica de la Defensa Francesa. Se busca equilibrio en el centro.",
      "pros": "Disputa el centro, estructura sólida.",
      "cons": "Posible presión en e5."
    },
    {
      "san": "Nd2",
      "title": "3. Nd2 — Variante Tarrasch",
      "explanation": "El caballo se desarrolla sin bloquear el peón c. Esta jugada mantiene flexibilidad y evita líneas más teóricas. También prepara Ngf3.",
      "pros": "Desarrollo flexible, evita teoría pesada.",
      "cons": "Caballo algo pasivo inicialmente."
    },
    {
      "san": "c5",
      "title": "3... c5 — Presión sobre el centro",
      "explanation": "Las negras atacan el centro blanco desde el flanco. Es una idea típica en la Francesa. Busca debilitar d4.",
      "pros": "Presión dinámica, rompe el centro.",
      "cons": "Puede dejar debilidades si no se maneja bien."
    },
    {
      "san": "exd5",
      "title": "4. exd5 — Simplificación central",
      "explanation": "Las blancas deciden intercambiar en el centro. Esto reduce la tensión y abre líneas. También busca explotar el desarrollo.",
      "pros": "Apertura de líneas, simplificación.",
      "cons": "Pierde control de espacio central."
    },
    {
      "san": "Qxd5",
      "title": "4... Qxd5 — Recuperación activa",
      "explanation": "La dama recupera el peón rápidamente. Aunque activa, puede ser objeto de ataques. Es una elección práctica.",
      "pros": "Recupera material, activa la dama.",
      "cons": "Dama expuesta a ataques de desarrollo."
    },
    {
      "san": "Ngf3",
      "title": "5. Ngf3 — Desarrollo con iniciativa",
      "explanation": "Las blancas desarrollan pieza atacando la dama. También preparan el enroque. Ganar tiempos es clave aquí.",
      "pros": "Desarrollo, gana tiempo.",
      "cons": "Ninguna significativa."
    },
    {
      "san": "cxd4",
      "title": "5... cxd4 — Captura central",
      "explanation": "Las negras ganan un peón temporalmente. Buscan aprovechar el momento. Sin embargo, el desarrollo blanco será más rápido.",
      "pros": "Ganancia material temporal.",
      "cons": "Retraso en desarrollo."
    },
    {
      "san": "Bc4",
      "title": "6. Bc4 — Desarrollo activo",
      "explanation": "El alfil apunta a f7, una casilla débil. Se desarrolla con iniciativa. También presiona indirectamente.",
      "pros": "Presión táctica, desarrollo activo.",
      "cons": "Puede ser atacado."
    },
    {
      "san": "Qh5",
      "title": "6... Qh5 — Defensa y actividad",
      "explanation": "La dama se retira manteniendo presión. Evita ataques inmediatos. Sin embargo, sigue siendo vulnerable.",
      "pros": "Mantiene actividad.",
      "cons": "Dama sigue expuesta."
    }
  ]
}